.gitignore
CHANGES.txt
MANIFEST.in
README.txt
setup.py
wicked-configure.zcml
wicked-meta.zcml
wicked.atcontent-configure.zcml
docs/DETAILS.txt
docs/INSTALL.txt
docs/LICENSE.GPL
docs/LICENSE.txt
docs/LINKS.txt
docs/MIGRATION.txt
docs/Makefile
docs/README.txt
docs/REQUIREMENTS.txt
docs/TODO.txt
docs/style.css
wicked/README.txt
wicked/TODO.txt
wicked/__init__.py
wicked/basic-example.zcml
wicked/cache.py
wicked/cache.txt
wicked/config.py
wicked/configure.zcml
wicked/decorator_intro.txt
wicked/event.py
wicked/interfaces.py
wicked/link.py
wicked/link.txt
wicked/normalize.py
wicked/registration.py
wicked/site.py
wicked/tests.py
wicked/txtfilter-example.zcml
wicked/txtfilter.py
wicked/utils.py
wicked/vocabularies.zcml
wicked/wicked_link.pt
wicked.egg-info/PKG-INFO
wicked.egg-info/SOURCES.txt
wicked.egg-info/dependency_links.txt
wicked.egg-info/entry_points.txt
wicked.egg-info/namespace_packages.txt
wicked.egg-info/not-zip-safe
wicked.egg-info/requires.txt
wicked.egg-info/top_level.txt
wicked/at/README.txt
wicked/at/__init__.py
wicked/at/add.txt
wicked/at/backlink.py
wicked/at/config.py
wicked/at/configure.zcml
wicked/at/field.py
wicked/at/interfaces.py
wicked/at/link.py
wicked/at/objectevents.zcml
wicked/at/relation.py
wicked/at/renderer.txt
wicked/at/seeker.py
wicked/at/subscriber.py
wicked/at/zope2.py
wicked/at/Extensions/Install.py
wicked/at/Extensions/__init__.py
wicked/at/Extensions/upgrade.py
wicked/at/tests/__init__.py
wicked/at/tests/test_cache.py
wicked/at/tests/test_linking.py
wicked/at/tests/test_rendering.py
wicked/at/tests/test_scope.py
wicked/at/tests/wickedtestcase.py
wicked/atcontent/README.txt
wicked/atcontent/__init__.py
wicked/atcontent/configure.zcml
wicked/atcontent/interfaces.py
wicked/atcontent/ironicwiki.py
wicked/atcontent/permissions.py
wicked/atcontent/tests.py
wicked/atcontent/wickeddoc.py
wicked/atcontent/zope2.py
wicked/atcontent/Extensions/Install.py
wicked/atcontent/Extensions/__init__.py
wicked/atcontent/Extensions/migrate_atdoc_wickeddoc.py
wicked/atcontent/migration/__init__.py
wicked/atcontent/migration/migrator.py
wicked/fieldevent/README.txt
wicked/fieldevent/__init__.py
wicked/fieldevent/configure.zcml
wicked/fieldevent/interfaces.py
wicked/fieldevent/meta.py
