Metadata-Version: 1.1
Name: wicked
Version: 1.1.11
Summary: wicked is a compact syntax for doing wiki-like content linking and creation in zope and plone
Home-page: http://pypi.python.org/pypi/wicked
Author: whit
Author-email: wicked@lists.openplans.org
License: GPL
Keywords: wiki anti-wiki zope2 plone
Platform: UNKNOWN
Classifier: Framework :: Zope2
Classifier: Framework :: Plone
Classifier: Programming Language :: Python
